mcp_memory_py/__init__.py
mcp_memory_py/__main__.py
mcp_memory_py/knowledge_graph.py
mcp_memory_py/logging.py
mcp_memory_py/server.py
mcp_memory_py-0.2.1.dist-info/METADATA
mcp_memory_py-0.2.1.dist-info/WHEEL
mcp_memory_py-0.2.1.dist-info/entry_points.txt
mcp_memory_py-0.2.1.dist-info/licenses/LICENSE
mcp_memory_py-0.2.1.dist-info/RECORD
