Metadata-Version: 2.4
Name: mcp-memory-py
Version: 0.2.1
Summary: MCP server for enabling memory for Claude through a knowledge graph
License-Expression: MIT
License-File: LICENSE
Requires-Python: >=3.12
Requires-Dist: mcp[cli]>=1.2.1
